Metadata-Version: 2.1
Name: pysfish
Version: 0.0.3
Summary: Seirawan-Stockfish Python wrapper
Home-page: https://github.com/gbtami/Seirawan-Stockfish
Author: Bajusz Tamás
Author-email: gbtami@gmail.com
License: GPL3
Platform: UNKNOWN
Classifier: Development Status :: 3 - Alpha
Classifier: License :: OSI Approved :: GNU General Public License v3 (GPLv3)
Classifier: Programming Language :: Python :: 3
Classifier: Operating System :: OS Independent
